cux/__init__.py
cux-0.2.2.dist-info/METADATA
cux-0.2.2.dist-info/WHEEL
cux-0.2.2.dist-info/top_level.txt
cux-0.2.2.dist-info/RECORD
