Metadata-Version: 2.1
Name: cux
Version: 0.2.2
Summary: ok
Author: slipper
Author-email: r2fscg@gmail.com
Classifier: Programming Language :: Python :: 3
Classifier: License :: OSI Approved :: MIT License
Classifier: Operating System :: OS Independent
